visio_rust-0.2.2.dist-info/METADATA
visio_rust-0.2.2.dist-info/WHEEL
visio_rust/__init__.py
visio_rust/__init__.pyi
visio_rust/py.typed
visio_rust/visio_rust.cpython-37m-x86_64-linux-gnu.so
visio_rust-0.2.2.dist-info/RECORD
