Metadata-Version: 2.1
Name: visio_rust
Version: 0.2.2
Classifier: Programming Language :: Python
Classifier: Programming Language :: Rust
Classifier: Intended Audience :: Developers
Classifier: Operating System :: MacOS :: MacOS X
Classifier: Operating System :: Microsoft :: Windows
Classifier: Operating System :: POSIX :: Linux
Classifier: Operating System :: POSIX
Classifier: Operating System :: Unix
Summary: Rust plugin for python exif and icc profile manipulation
Maintainer-email: Anderson Cançado <anderson.cancado@gaspardbruno.com>, Marco João <marco.joao@gaspardbruno.com>
Requires-Python: >=3.7
Project-URL: tracker, https://github.com/Gaspard-Bruno/visio-rust/issues
Project-URL: homepage, https://github.com/Gaspard-Bruno/visio-rust
Project-URL: source, https://github.com/Gaspard-Bruno/visio-rust
